mesi/__init__.py
mesi/__main__.py
mesi/compare.py
mesi/display.py
mesi/main.py
mesi/prepare.py
mesi/verify.py
mesi-1.1.0.dist-info/entry_points.txt
mesi-1.1.0.dist-info/LICENSE
mesi-1.1.0.dist-info/WHEEL
mesi-1.1.0.dist-info/METADATA
mesi-1.1.0.dist-info/RECORD
