Metadata-Version: 2.1
Name: mesi
Version: 1.1.0
Summary: Measure similarity in a many-to-many fashion
Home-page: https://github.com/Michionlion/mesi
License: GPL-3.0-or-later
Keywords: diff,similarity,check
Author: Saejin Mahlau-Heinert
Author-email: saejinmh@gmail.com
Requires-Python: >=3.6.2,<4.0
Classifier: Development Status :: 5 - Production/Stable
Classifier: Environment :: Console
Classifier: License :: OSI Approved :: GNU General Public License v3 or later (GPLv3+)
Classifier: Operating System :: OS Independent
Classifier: Programming Language :: Python :: 3
Classifier: Programming Language :: Python :: 3.7
Classifier: Programming Language :: Python :: 3.8
Classifier: Programming Language :: Python :: 3.9
Classifier: Programming Language :: Python :: 3.10
Classifier: Topic :: Education :: Testing
Classifier: Topic :: Text Processing :: General
Classifier: Topic :: Utilities
Classifier: Typing :: Typed
Requires-Dist: importlib-metadata (<4.3)
Requires-Dist: polyleven (>=0.7,<0.8)
Requires-Dist: tabulate (>=0.8.9,<0.9.0)
Requires-Dist: textdistance[extras] (>=4.2.1,<5.0.0)
Requires-Dist: tqdm (>=4.62.3,<5.0.0)
Requires-Dist: typer[all] (>=0.4.0,<0.5.0)
Project-URL: Bug Tracker, https://github.com/Michionlion/mesi/issues
Project-URL: Documentation, https://github.com/Michionlion/mesi
Project-URL: Repository, https://github.com/Michionlion/mesi
